eval_python_2_mdhcquete_v3/__init__.py
eval_python_2_mdhcquete_v3/__main__.py
eval_python_2_mdhcquete_v3/main.py
eval_python_2_mdhcquete_v3-1.0.dist-info/LICENSE
eval_python_2_mdhcquete_v3-1.0.dist-info/METADATA
eval_python_2_mdhcquete_v3-1.0.dist-info/WHEEL
eval_python_2_mdhcquete_v3-1.0.dist-info/entry_points.txt
eval_python_2_mdhcquete_v3-1.0.dist-info/top_level.txt
eval_python_2_mdhcquete_v3-1.0.dist-info/RECORD
