Metadata-Version: 2.1
Name: eval_python_2_mdhcquete_v3
Version: 1.0
Summary: Evaluacion Python Nivel II
Home-page: https://github.com/mrcsd-hrrr
Author: Marcos Daniel Herrera Cervantes
Author-email: mrcsd.hrrr@gmail.com
Classifier: Programming Language :: Python :: 3
Classifier: License :: OSI Approved :: MIT License
Classifier: Operating System :: OS Independent
License-File: LICENSE
Requires-Dist: requests
Requires-Dist: pillow
Requires-Dist: matplotlib
